MANIFEST.in
README.rst
setup.py
docs/HISTORY.txt
docs/LICENSE.GPL
docs/LICENSE.txt
ftw/__init__.py
ftw.geo.egg-info/PKG-INFO
ftw.geo.egg-info/SOURCES.txt
ftw.geo.egg-info/dependency_links.txt
ftw.geo.egg-info/entry_points.txt
ftw.geo.egg-info/namespace_packages.txt
ftw.geo.egg-info/not-zip-safe
ftw.geo.egg-info/requires.txt
ftw.geo.egg-info/top_level.txt
ftw/geo/__init__.py
ftw/geo/configure.zcml
ftw/geo/handlers.py
ftw/geo/interfaces.py
ftw/geo/setuphandlers.py
ftw/geo/testing.py
ftw/geo/locales/ftw.geo.pot
ftw/geo/locales/de/LC_MESSAGES/ftw.geo.po
ftw/geo/profiles/default/ftw.geo_default.txt
ftw/geo/profiles/default/metadata.xml
ftw/geo/profiles/default/registry.xml
ftw/geo/tests/__init__.py
ftw/geo/tests/helpers.py
ftw/geo/tests/test.zcml
ftw/geo/tests/test_archetypes.py
ftw/geo/tests/test_dexterity.py
ftw/geo/tests/test_geocoding.py
ftw/geo/tests/utils.py
ftw/geo/upgrades/__init__.py
ftw/geo/upgrades/configure.zcml
ftw/geo/upgrades/to1000.py