Metadata-Version: 2.1
Name: ftw.geo
Version: 1.4.1
Summary: Integration package for collective.geo.* packages.
Home-page: https://github.com/4teamwork/ftw.geo
Author: 4teamwork AG
Author-email: mailto:info@4teamwork.ch
Maintainer: Lukas Graf
License: GPL2
Keywords: plone ftw geo
Platform: UNKNOWN
Classifier: Framework :: Plone
Classifier: Framework :: Plone :: 4.3
Classifier: Framework :: Plone :: 5.1
Classifier: Intended Audience :: Developers
Classifier: License :: OSI Approved :: GNU General Public License (GPL)
Classifier: Programming Language :: Python
Classifier: Topic :: Software Development
Provides-Extra: tests
